pharokka-1.8.1.data/scripts/citation.py
pharokka-1.8.1.data/scripts/create_custom_hmm.py
pharokka-1.8.1.data/scripts/custom_db.py
pharokka-1.8.1.data/scripts/databases.py
pharokka-1.8.1.data/scripts/external_tools.py
pharokka-1.8.1.data/scripts/hmm.py
pharokka-1.8.1.data/scripts/input_commands.py
pharokka-1.8.1.data/scripts/install_databases.py
pharokka-1.8.1.data/scripts/pharokka.py
pharokka-1.8.1.data/scripts/pharokka_multiplotter.py
pharokka-1.8.1.data/scripts/pharokka_plotter.py
pharokka-1.8.1.data/scripts/pharokka_proteins.py
pharokka-1.8.1.data/scripts/plot.py
pharokka-1.8.1.data/scripts/post_processing.py
pharokka-1.8.1.data/scripts/processes.py
pharokka-1.8.1.data/scripts/proteins.py
pharokka-1.8.1.data/scripts/util.py
pharokka-1.8.1.data/scripts/version.py
pharokka-1.8.1.dist-info/licenses/AUTHORS.md
pharokka-1.8.1.dist-info/licenses/LICENSE
pharokka_runner/citation.py
pharokka_runner/create_custom_hmm.py
pharokka_runner/custom_db.py
pharokka_runner/databases.py
pharokka_runner/external_tools.py
pharokka_runner/hmm.py
pharokka_runner/input_commands.py
pharokka_runner/install_databases.py
pharokka_runner/pharokka.py
pharokka_runner/pharokka_multiplotter.py
pharokka_runner/pharokka_plotter.py
pharokka_runner/pharokka_proteins.py
pharokka_runner/plot.py
pharokka_runner/post_processing.py
pharokka_runner/processes.py
pharokka_runner/proteins.py
pharokka_runner/run_pyrodigal_gv.py
pharokka_runner/util.py
pharokka_runner/version.py
pharokka-1.8.1.dist-info/METADATA
pharokka-1.8.1.dist-info/WHEEL
pharokka-1.8.1.dist-info/top_level.txt
pharokka-1.8.1.dist-info/RECORD
