Metadata-Version: 2.4
Name: pharokka
Version: 1.8.1
Summary: Fast phage annotation tool
Author-email: George Bouras <george.bouras@adelaide.edu.au>
License: MIT
Requires-Python: >=3.5
License-File: LICENSE
License-File: AUTHORS.md
Requires-Dist: setuptools<81,>=67.7.2
Requires-Dist: loguru>=0.5.4
Requires-Dist: pyyaml>=6.0
Requires-Dist: pandas>=1.4.2
Requires-Dist: biopython>=1.80
Requires-Dist: pyhmmer>=0.10.0
Requires-Dist: black>=22.3.0
Requires-Dist: isort>=5.10.1
Requires-Dist: pytest>=6.2.5
Requires-Dist: pytest-cov>=3.0.0
Requires-Dist: alive-progress>=3.0.1
Requires-Dist: requests>=2.25.1
Requires-Dist: bcbio-gff>=0.7.0
Requires-Dist: pyrodigal>=3.0.0
Requires-Dist: pyrodigal_gv>=0.1.0
Requires-Dist: phanotate<2,>=1.6.7
Dynamic: license-file
